{
    "common_metadata": {
        "report_type": "종목분석",
        "report_date": "2026-02-10",
        "brokerage": "교보증권",
        "analyst_name": "김광식, 최보영",
        "report_title": "2026년 2월 둘째 주 자동차이차전지 Weekly"
    },
    "specific_data": {
        "sector_name": "자동차/이차전지",
        "industry_rating": null,
        "top_picks": [
            "현대차",
            "기아",
            "LG에너지솔루션",
            "삼성SDI"
        ],
        "industry_trends": [
            "Stellantis: 220억 유로 손실 반영, 레거시 OE 전략 전환기에 경쟁력 유지 업체 주목 필요",
            "BYD: 1월 판매량 30% 급감, 시장 둔화 지속으로 신생 브랜드의 신규 시장 개척 수요 강화",
            "스페인 Auto+ 발표: 저가형 추가 인센티브 적용, 정책 회복으로 유럽 EV 판매 증분 지속",
            "2025년 글로벌 국내 3사 EV 배터리 점유율 하락. LGES 9.2%, SKon: 3.7% 삼성SDI: 2.4%",
            "2025년 1~12월 글로벌 전기차용 배터리 양극재 적재량 2,649K ton, 전년 동기 대비 35.3% 성장",
            "글로벌 휴머노이드 로봇, 2040년 5,300만대, 배터리 수요 150GWh 전망",
            "2025년 글로벌 EV 배터리 시장 점유율: CATL 39.2%, BYD 16.4%"
        ],
        "risk_factors": [
            "미국 관세 인상 불안감",
            "소프트웨어 문제로 인한 리콜",
            "글로벌 시장 둔화"
        ]
    }
}