{
    "common_metadata": {
        "report_type": "산업분석",
        "report_date": "2026-02-25",
        "brokerage": "유안타증권",
        "analyst_name": "권명준",
        "report_title": "페로브스카이트, 국내 기업들이 주목받을 수 .."
    },
    "specific_data": {
        "sector_name": "스몰캡",
        "industry_rating": null,
        "top_picks": [
            "필옵틱스",
            "신성이엔지"
        ],
        "industry_trends": [
            "페로브스카이트 태양전지에 대한 연구가 활발히 진행되고 있음",
            "국내 기업들이 태양전지 제조를 위한 기술을 보유하고 있음",
            "정부의 태양전지 지원 확대"
        ],
        "risk_factors": [
            "페로브스카이트의 안정성 문제",
            "환경오염 우려",
            "대량양산 및 대면적 적용의 어려움"
        ]
    }
}