{
    "common_metadata": {
        "report_type": "시황정보",
        "report_date": "2026-03-13",
        "brokerage": "null",
        "analyst_name": "null",
        "report_title": "[Morning Brief] 국제 유가 급등에 물가 우려 확대되.."
    },
    "specific_data": {
        "market_summary": "국제 유가 급등에 물가 우려 확대되며 미 증시 하락 마감. 국내 증시는 혼조 마감하며 코스피는 -0.48%, 코스닥은 +1.02%로 마감. 반도체, 하드웨어, 조선 업종 등 대체로 상승 마감.",
        "macro_indicators": "미국 1월 개인소비지출, 미국 1월 노동부 JOLTs, 미국 3월 미시건대 소비자심리지수",
        "fund_flows": "MSCI 한국 ETF -7.04% 급락, MSCI 신흥시장 ETF -3.20% 상승",
        "key_news": [
            "국제 유가 급등 소식에 기술주 중심의 투매 발생",
            "미국 희토류 재고 부족으로 유니온머티리얼즈 등 희토류 업종 상승",
            "달러-원 환율은 서울 외환시장에서 1,481.10원으로 마감"
        ]
    }
}