{
    "common_metadata": {
        "report_type": "시황정보",
        "report_date": "2026-02-09",
        "brokerage": "KB증권",
        "analyst_name": "임정은, 태윤선",
        "report_title": "29 KB 리서치 모닝코멘트"
    },
    "specific_data": {
        "market_summary": "국내 및 글로벌 증시 동향",
        "macro_indicators": "미국 10년물 국채 수익률 4.21%, 달러 인덱스 97.63, 유가 63.55달러/배럴",
        "fund_flows": "낙폭과대인식에 따른 저가 매수세와 비트코인 급반등에 위험 선호 심리 확산",
        "key_news": [
            "구글, 아마존 등 빅테크들이 올해 AI 인프라 구축 자본 지출을 예상보다 확대한다는 소식",
            "2월 미시간 대 소비자 심리지수 예비치 57.3으로 1월(56.4)보다 상승, 예상치(55.0) 상회"
        ]
    }
}