{
    "common_metadata": {
        "report_type": "시황정보",
        "report_date": "2026-02-02",
        "brokerage": "대신증권",
        "analyst_name": null,
        "report_title": "Daishin’s View"
    },
    "specific_data": {
        "strategy_theme": "금리 및 환율 전망, 반도체 및 주식 시장 전망",
        "recommended_portfolio": [
            "삼성전자",
            "삼성바이오로직스",
            "기아",
            "한국전력",
            "하나금융지주",
            "카카오",
            "LS ELECTRIC",
            "KT",
            "두산",
            "한국금융지주"
        ],
        "strategy_logic": [
            "한국 기준금리 인하 사이클 종료 후 변동성 위험",
            "미국 장기국채 물량 소화 여부 주목",
            "반도체 주도 실적 전망 레벨업",
            "KOSPI 상승 여력 확대",
            "선진국 시장 비중 확대"
        ],
        "quant_factors": [
            "KOSPI 12M Fwd EPS",
            "기준금리",
            "환율",
            "국고채 발행량",
            "국내외 경제 성장률"
        ]
    }
}