{
    "common_metadata": {
        "report_type": "시황정보",
        "report_date": "2026-02-12",
        "brokerage": "IBK투자증권",
        "analyst_name": "변준호",
        "report_title": "[IBKS Market Comment] 3월 기대감 지속, KOSPI 상단 .."
    },
    "specific_data": {
        "strategy_theme": "3월 기대감 지속, KOSPI 상단 상향",
        "recommended_portfolio": null,
        "strategy_logic": [
            "3월 FOMC 금리 동결 예상",
            "단기 과열 해소 후 재 상승 기조",
            "3월 주주총회 기대감",
            "3월 이익조정비율 상승 기대감",
            "4월 WGBI 편입으로 인한 원화 강세 기대감"
        ],
        "quant_factors": [
            "KOSPI 12M F. ROE 16.5%",
            "삼성전자 12M F. ROE 24%",
            "KOSPI P/B 1.67배",
            "KOSPI 12M F. P/E 9배"
        ]
    }
}