{
    "common_metadata": {
        "report_type": "종목분석",
        "report_date": "2026-02-12",
        "brokerage": "키움증권",
        "analyst_name": "허혜민",
        "report_title": "킥(kick)이 없다구요 #안나오는 OS, #API 증.."
    },
    "specific_data": {
        "company_name": "유한양행",
        "ticker": "000100",
        "investment_rating": null,
        "investment_points": [
            "4분기 실적은 당사 기대치에 대체로 부합",
            "렉라자 병용요법 발표 시점이 핵심",
            "성과 확인될 때마다 계단식 우상향 전망"
        ],
        "risk_factors": [
            "정부의 약가개편 불확실성",
            "렉라자 병용요법 처방의 급격한 성장 확인 지연"
        ],
        "shareholder_structure": "주요 주주 지분율에 대한 정보는 제공되지 않음"
    }
}