{
    "common_metadata": {
        "report_type": "종목분석",
        "report_date": "2026-02-20",
        "brokerage": "유진투자증권",
        "analyst_name": "박종선",
        "report_title": "4Q25P Review 수출 회복 지속 긍정적"
    },
    "specific_data": {
        "company_name": "바텍",
        "ticker": "043150",
        "investment_rating": "BUY",
        "investment_points": [
            "유럽과 아시아 지역을 중심으로 전년동기 대비 매출 성장 견인",
            "분기 최대 매출액 달성",
            "수익성 개선"
        ],
        "risk_factors": [
            "북아메리카 지역에서 매출 감소",
            "글로벌 경제 불확실성"
        ],
        "shareholder_structure": "바텍이우홀딩스 53.7%, FIDELITY MANAGEMENT 8.1%, Swedbank Robur Fonder AB 5.1%"
    }
}